hikaru_microservice/__init__.py
hikaru_microservice-1.0.1.dist-info/METADATA
hikaru_microservice-1.0.1.dist-info/WHEEL
hikaru_microservice-1.0.1.dist-info/licenses/LICENSE
hikaru_microservice-1.0.1.dist-info/RECORD
