Metadata-Version: 2.3
Name: hikaru-microservice
Version: 1.0.1
Summary: Python package that provides the base for Hikaru FastAPI microservices.
Project-URL: Homepage, https://github.com/mizu-hikaru/hikaru-microservice
Project-URL: Issues, https://github.com/mizu-hikaru/hikaru-microservice/issues
Author-email: Mizu Hikaru <mizu@hikaru.org>
License-File: LICENSE
Classifier: License :: OSI Approved :: MIT License
Classifier: Operating System :: OS Independent
Classifier: Programming Language :: Python :: 3
Requires-Python: >=3.9
Requires-Dist: fastapi[standard]
